TikTokApi/__init__.py
TikTokApi/exceptions.py
TikTokApi/helpers.py
TikTokApi/tiktok.py
TikTokApi/utilities.py
TikTokApi/api/__init__.py
TikTokApi/api/comment.py
TikTokApi/api/hashtag.py
TikTokApi/api/search.py
TikTokApi/api/sound.py
TikTokApi/api/trending.py
TikTokApi/api/user.py
TikTokApi/api/video.py
TikTokApi/browser_utilities/__init__.py
TikTokApi/browser_utilities/browser.py
TikTokApi/browser_utilities/browser_interface.py
TikTokApi/browser_utilities/get_acrawler.py
examples/__init__.py
examples/comment_example.py
examples/hashtag_example.py
examples/search_example.py
examples/sound_example.py
examples/trending_example.py
examples/user_example.py
examples/video_example.py
tests/__init__.py
tests/test_comments.py
tests/test_hashtag.py
tests/test_integration.py
tests/test_search.py
tests/test_sound.py
tests/test_trending.py
tests/test_user.py
tests/test_video.py
TikTokApi_Async-5.2.2.dist-info/LICENSE
TikTokApi_Async-5.2.2.dist-info/LICENSE.txt
TikTokApi_Async-5.2.2.dist-info/METADATA
TikTokApi_Async-5.2.2.dist-info/WHEEL
TikTokApi_Async-5.2.2.dist-info/top_level.txt
TikTokApi_Async-5.2.2.dist-info/RECORD
