Metadata-Version: 2.1
Name: TikTokApi-Async
Version: 5.2.2
Summary: The Unofficial TikTok API Wrapper in Python 3. (async)
Home-page: https://github.com/hackerman-rs/tiktokapi-async
Author: Violet McKinney
Author-email: tiktokapi-async@viomck.com
License: MIT
Keywords: tiktok,python3,api,unofficial,tiktok-api,tiktok api
Classifier: Development Status :: 3 - Alpha
Classifier: Intended Audience :: Developers
Classifier: Topic :: Software Development :: Build Tools
Classifier: License :: OSI Approved :: MIT License
Classifier: Programming Language :: Python :: 3.7
Classifier: Programming Language :: Python :: 3.8
Classifier: Programming Language :: Python :: 3.9
Classifier: Programming Language :: Python :: 3.10
License-File: LICENSE
License-File: LICENSE.txt
